ske19_api/__init__.py
ske19_api/ske19.py
ske19_api/student.py
ske19_api-1.1.1.dist-info/METADATA
ske19_api-1.1.1.dist-info/WHEEL
ske19_api-1.1.1.dist-info/top_level.txt
ske19_api-1.1.1.dist-info/RECORD
