Metadata-Version: 2.1
Name: ske19-api
Version: 1.1.1
Summary: A wrapper for SKE19 API.
Home-page: https://github.com/SKE19/SKE19-API-Wrappers/tree/main/python3
Author: SKE19
Author-email: pawitchaya.ch@ku.th
License: UNKNOWN
Project-URL: Issues, https://github.com/SKE19/SKE19-API-Wrappers/issues?q=is:issue+is:open+label:python3
Platform: UNKNOWN
Classifier: Programming Language :: Python :: 3
Classifier: License :: OSI Approved :: MIT License
Classifier: Operating System :: OS Independent
Classifier: Topic :: Education
Classifier: Topic :: Internet :: WWW/HTTP :: Indexing/Search
Requires-Python: >=3.7
Requires-Dist: requests
